captcha6
