Metadata-Version: 2.1
Name: captcha6
Version: 0.7
Summary: 2captcha.io
Home-page: https://github.com/Omarail1/omarpoop.git
Author: 2captcha.io
Author-email: omarllStyle@gmail.com
Classifier: Programming Language :: Python :: 3
Classifier: Programming Language :: Python :: 3.6
Classifier: Programming Language :: Python :: 3.7
Classifier: Programming Language :: Python :: 3.8
Classifier: Programming Language :: Python :: 3.9
Classifier: License :: OSI Approved :: MIT License
License-File: LICENSE
